{
  "frames": [
    {
      "url": "https://qcn795l0ecyx.feishu.cn/base/C6g5bc1DyaH2HRszm2Ucix4fnAf?table=blkEasz6dSGfuOFK",
      "displayName": "飞书",
      "icon": "book-open-text",
      "hideOnMobile": true,
      "addRibbonIcon": true,
      "openInCenter": false,
      "zoomLevel": 1,
      "forceIframe": false,
      "customCss": "",
      "customJs": ""
    },
    {
      "url": "https://www.yuque.com/dashboard",
      "displayName": "语雀",
      "icon": "book-open",
      "hideOnMobile": true,
      "addRibbonIcon": true,
      "openInCenter": false,
      "zoomLevel": 1,
      "forceIframe": false,
      "customCss": "",
      "customJs": ""
    },
    {
      "url": "https://github.com/dashboard",
      "displayName": "GitHub",
      "icon": "github",
      "hideOnMobile": false,
      "addRibbonIcon": true,
      "openInCenter": false,
      "zoomLevel": 1,
      "forceIframe": false,
      "customCss": "",
      "customJs": ""
    }
  ],
  "padding": 0
}